[
  {
    "sku": "104203",
    "name": "Cimento Endodôntico BioRoot RCS - Septodont",
    "description": "Embalagem com 1 pó de 15g + 35 Ampolas e 1 Colher Medidora.",
    "image": "https://cdn.dentalcremer.com.br/produtos/210/cimento-endodontico-bioroot-rcs-septodont-104203.jpg",
    "url": "https://www.dentalcremer.com.br/cimento-endodontico-bioroot-rcs-septodont-104203.html"
  },
  {
    "sku": "126339",
    "name": "Broca Lentulo 21mm Nº 25-40 CA - Mani",
    "description": "Embalagem com 4 unidades. 21mm de comprimento cada.",
    "image": "https://cdn.dentalcremer.com.br/produtos/210/broca-lentulo-21mm-n-25-40-ca-mani-126339-dental-cremer.jpg",
    "url": "https://www.dentalcremer.com.br/broca-lentulo-21mm-n-25-40-ca-mani-126339.html"
  },
  {
    "sku": "DC27187",
    "name": "Broca Carbide Esférica AR - Jet",
    "description": "Embalagem com 5 unidades. Baixa Rotação.",
    "image": "https://cdn.dentalcremer.com.br/produtos/210/168198_2.jpg",
    "url": "https://www.dentalcremer.com.br/broca-carbide-esferica-ar-jet-dc27187.html"
  },
  {
    "sku": "126321",
    "name": "Espaçador Digital NiTi 25mm ABCD - Dentsply Sirona",
    "description": "Blister com 04 unidades de 25mm de comprimento cada, nos tamanhos A,B,C e D (sendo 1 de cada).",
    "image": "https://cdn.dentalcremer.com.br/produtos/210/espacador-digital-niti-25mm-abcd-dentsply-sirona-126321.jpg",
    "url": "https://www.dentalcremer.com.br/espacador-digital-niti-25mm-abcd-dentsply-sirona-126321.html"
  },
  {
    "sku": "389067",
    "name": "Broca Lentulo CA - Mani",
    "description": "Embalagem com 4 unidades.",
    "image": "https://cdn.dentalcremer.com.br/produtos/210/389067.jpg",
    "url": "https://www.dentalcremer.com.br/broca-lentulo-mani-wilcos-389067.html"
  },
  {
    "sku": "DC13261",
    "name": "Broca de Aço Cônica Batt - Injecta",
    "description": "Embalagem com 6 unidades.",
    "image": "https://cdn.dentalcremer.com.br/produtos/210/487169.jpg",
    "url": "https://www.dentalcremer.com.br/broca-de-aco-conica-batt-injecta-dc13261.html"
  },
  {
    "sku": "DC18777",
    "name": "Broca Peeso CA - Meisinger",
    "description": "Embalagem com 1 unidade. 34mm.",
    "image": "https://cdn.dentalcremer.com.br/produtos/210/685503_635905315572767519.jpg",
    "url": "https://www.dentalcremer.com.br/broca-peeso-ca-meisinger-wilcos-dc18777.html"
  },
  {
    "sku": "107231",
    "name": "Broca Endo Z  FG Invicta - American Burrs",
    "description": "Unidade. Alta rotação. 23mm.",
    "image": "https://cdn.dentalcremer.com.br/produtos/210/broca-carbide-endo-z-152-fg-invicta-american-burrs-dental-cremer-107231.jpg",
    "url": "https://www.dentalcremer.com.br/broca-endo-z-fg-invicta-american-burrs-107231.html"
  },
  {
    "sku": "868418",
    "name": "Broca Endo Z Mastercut - Wilcos",
    "description": "Embalagem com 1 unidade. HM 152.",
    "image": "https://cdn.dentalcremer.com.br/produtos/210/868418.jpg",
    "url": "https://www.dentalcremer.com.br/broca-endo-z-mastercut-wilcos-868418.html"
  },
  {
    "sku": "138002",
    "name": "Tamborel de Alumínio - Iodontosul",
    "description": "Embalagem com 1 unidade.",
    "image": "https://cdn.dentalcremer.com.br/produtos/210/tamborel-de-aluminio-iodontosul-dental-cremer-138002.jpg",
    "url": "https://www.dentalcremer.com.br/tamborel-de-aluminio-iodontosul-138002.html"
  },
  {
    "sku": "148724",
    "name": "Lima Rotatória Logic cm 30.03 31mm - Easy",
    "description": "Embalagem com 4 unidades.",
    "image": "https://cdn.dentalcremer.com.br/produtos/210/lima-rotatoria-logic-cm-30-03-31mm-easy-148724.jpg",
    "url": "https://www.dentalcremer.com.br/lima-rotatoria-logic-cm-30-03-31mm-easy-148724.html"
  },
  {
    "sku": "DC39113",
    "name": "Lima Manual M 21mm 1ª Série 15-40 - Easy",
    "description": "Embalagem com 6 unidades sortidas.",
    "image": "https://cdn.dentalcremer.com.br/produtos/210/lima-manual-m-31mm-1-serie-15-40-easy-dc39115.jpg",
    "url": "https://www.dentalcremer.com.br/lima-manual-m-21mm-1-serie-15-40-easy-dc39113.html"
  },
  {
    "sku": "130532",
    "name": "Hidróxido de Cálcio com PMCC 1,76g - Fórmula & Ação",
    "description": "Embalagem com 1 seringa de 1,76g e 5 ponteiras aplicadoras.",
    "image": "https://cdn.dentalcremer.com.br/produtos/210/hidroxido-de-calcio-com-pmcc-1-76-formula-e-acao-130532-dental-cremer.jpg",
    "url": "https://www.dentalcremer.com.br/hidroxido-de-calcio-com-pmcc-1-76g-formula-e-ac-o-130532.html"
  },
  {
    "sku": "700527",
    "name": "Lençol de Borracha Optradam Plus Small - Ivoclar Vivadent",
    "description": "Embalagem com 50 unidades.",
    "image": "https://cdn.dentalcremer.com.br/produtos/210/lencol-de-borracha-optradam-plus-small-50unid--dental-cremer-700527.jpg",
    "url": "https://www.dentalcremer.com.br/lencol-de-borracha-optradam-plus-small-ivoclar-vivadent-700527.html"
  },
  {
    "sku": "119048",
    "name": "Régua Anel Endodôntica Milimetrada de Plastico com Tamborel - Mk Life",
    "description": "Embalagem com 1 unidade.",
    "image": "https://cdn.dentalcremer.com.br/produtos/210/regua-anel-endodontica-milimetrada-de-plastico-com-tamborel-mk-life-119048-dental-cremer.jpg",
    "url": "https://www.dentalcremer.com.br/regua-anel-endodontica-milimetrada-de-plastico-com-tamborel-mk-life-119048.html"
  },
  {
    "sku": "214321",
    "name": "Régua Plástica Milimetrada Endodôntica - Angelus",
    "description": "Embalagem com 1 unidade.",
    "image": "https://cdn.dentalcremer.com.br/produtos/210/214321.jpg",
    "url": "https://www.dentalcremer.com.br/regua-plastica-milimetrada-endodontica-angelus-214321.html"
  },
  {
    "sku": "126134",
    "name": "Régua Endodôntica Milimetrada 3 Furos - Odous de Deus",
    "description": "Embalagem com 1 unidade.",
    "image": "https://cdn.dentalcremer.com.br/produtos/210/regua-endodontica-milimetrada-com-3-furos-odous-de-deus-126134.jpg",
    "url": "https://www.dentalcremer.com.br/regua-endodontica-milimetrada-3-furos-odous-de-deus-126134.html"
  },
  {
    "sku": "116068",
    "name": "Lençol De Borracha Azul - Nictone",
    "description": "Embalagem com 3 unidades. 15,2x15,2cm.",
    "image": "https://cdn.dentalcremer.com.br/produtos/210/116068.jpg",
    "url": "https://www.dentalcremer.com.br/lencol-de-borracha-azul-15-2x15-2cm-nictone-116068.html"
  },
  {
    "sku": "841671",
    "name": "Ponta de Aspiração - Ice",
    "description": "Embalagem com 1 unidade. Média.",
    "image": "https://cdn.dentalcremer.com.br/produtos/210/841671.jpg",
    "url": "https://www.dentalcremer.com.br/ponta-de-aspirac-o-ice.html"
  },
  {
    "sku": "DC25175",
    "name": "Porta Lima Endo 16 Plástico - Prisma",
    "description": "Embalagem com 2 unidades. Escolha a cor.",
    "image": "https://cdn.dentalcremer.com.br/produtos/210/107852.jpg",
    "url": "https://www.dentalcremer.com.br/porta-lima-endo-16-plastico-prisma-dc25175.html"
  },
  {
    "sku": "387131",
    "name": "Sugador Endodôntico Flex Suctor - Angelus",
    "description": "Embalagem com 10 suctores esterilizados, 10 pontas de aspiração inicial (Endo Tips 0.06) e 10 pontas de aspiração final (Endo Tips 0.014).",
    "image": "https://cdn.dentalcremer.com.br/produtos/210/sugador-flex-suctor-endodontico-angelus-387131-dental-cremer.jpg",
    "url": "https://www.dentalcremer.com.br/flex-suctor-endodontico-angelus-1.html"
  },
  {
    "sku": "DC24364",
    "name": "Ponta de Aspiração - Fava",
    "description": "Embalagem com 1 unidade.",
    "image": "https://cdn.dentalcremer.com.br/produtos/210/772937.jpg",
    "url": "https://www.dentalcremer.com.br/ponta-de-aspirac-o-fava-dc24364.html"
  },
  {
    "sku": "126928",
    "name": "Pasta de Hidróxido de Cálcio Calcimol LC - Voco",
    "description": "Embalagem com 2 seringas de 2,5g cada e acessórios.",
    "image": "https://cdn.dentalcremer.com.br/produtos/210/pasta-hidroxido-calcio-calcimol-lc-voco-126928.jpg",
    "url": "https://www.dentalcremer.com.br/pasta-de-hidroxido-de-calcio-calcimol-lc-voco-126928.html"
  },
  {
    "sku": "958850",
    "name": "Lençol de Borracha Sanctuary - K-Dent",
    "description": "Embalagem com 26 unidades. Tamanho 15x15cm Médio. Preto.",
    "image": "https://cdn.dentalcremer.com.br/produtos/210/958850.jpg",
    "url": "https://www.dentalcremer.com.br/lencol-de-borracha-sanctuary-k-dent-958850.html"
  },
  {
    "sku": "133666",
    "name": "Condensador de Guta-Percha McSpadden Flex Pack 25mm Nº 45 - Easy",
    "description": "Embalagem com 3 unidades.",
    "image": "https://cdn.dentalcremer.com.br/produtos/210/condensadorguta-percha-mcspadden-flex-pack-25mm-n-45-easy-133666-att.jpg",
    "url": "https://www.dentalcremer.com.br/condensador-de-guta-percha-mcspadden-flex-pack-25mm-n-45-easy-133666.html"
  },
  {
    "sku": "145982",
    "name": "Adaptador de Sucção Luer Lock - Ice",
    "description": "Embalagem com 1 unidade.",
    "image": "https://cdn.dentalcremer.com.br/produtos/210/adaptador-de-succao-luer-lock-ice-145982-a.jpg",
    "url": "https://www.dentalcremer.com.br/adaptador-de-succao-luer-lock-ice-145982.html"
  },
  {
    "sku": "114742",
    "name": "Cimento Forrador de Hidróxido de Cálcio Hydcal - Technew",
    "description": "Embalagem com Base 13g + Catalisador 11g.",
    "image": "https://cdn.dentalcremer.com.br/produtos/210/kit-cimento-forrador-hidroxido-calcio-hydcal-technew-240269-dental-cremer-01.jpg",
    "url": "https://www.dentalcremer.com.br/cimento-forrador-de-hidroxido-de-calcio-hydcal-technew-114742.html"
  },
  {
    "sku": "133665",
    "name": "Condensador de Guta-Percha McSpadden Flex Pack 25mm Nº 40 - Easy",
    "description": "Embalagem com 3 unidades.",
    "image": "https://cdn.dentalcremer.com.br/produtos/210/condensador-de-guta-percha-mcspadden-flex-pack-25mm-n-40-easy-133665.jpg",
    "url": "https://www.dentalcremer.com.br/condensador-de-guta-percha-mcspadden-flex-pack-25mm-n-40-easy-133665.html"
  },
  {
    "sku": "295566",
    "name": "Vaselina Líquida - Rioquímica",
    "description": "Embalagem com 1000ml.MEDICAMENTO DE NOTIFICAÇÃO SIMPLIFICADA RDC Anvisa Nº 107/2016. AFE Nº 1.01.520-1.SE PERSISTIREM OS SINTOMAS, O MÉDICO DEVERÁ SER CONSULTADOÉ UM MEDICAMENTO. SEU USO PODE TRAZER RISCOS. PROCURE O MÉDICO E O FARMACÊUTICO. LEIA A BULA",
    "image": "https://cdn.dentalcremer.com.br/produtos/210/295566.jpg",
    "url": "https://www.dentalcremer.com.br/vaselina-liquida-rioquimica-295566.html"
  },
  {
    "sku": "133664",
    "name": "Condensador de Guta-Percha McSpadden Flex Pack 25mm Nº 35 - Easy",
    "description": "Embalagem com 3 unidades.",
    "image": "https://cdn.dentalcremer.com.br/produtos/210/condensador-de-guta-percha-mcspadden-flex-pack-25mm-n-35-3unid-easy-dental-cremer-133664.jpg",
    "url": "https://www.dentalcremer.com.br/condensador-de-guta-percha-mcspadden-flex-pack-25mm-n-35-easy-133664.html"
  },
  {
    "sku": "685220",
    "name": "Condensador de Guta Finger Spread - Mani",
    "description": "Embalagem com 6 unidades. N° 15-40.",
    "image": "https://cdn.dentalcremer.com.br/produtos/210/685220.jpg",
    "url": "https://www.dentalcremer.com.br/condensador-de-guta-finger-spread-mani-685220.html"
  },
  {
    "sku": "214314",
    "name": "Stop de Silicone Cursor - Angelus",
    "description": "Embalagem com 100 unidades (cursor). 1,5mm.",
    "image": "https://cdn.dentalcremer.com.br/produtos/210/214314.jpg",
    "url": "https://www.dentalcremer.com.br/stop-de-silicone-cursor-angelus-214314.html"
  },
  {
    "sku": "532579",
    "name": "Eucaliptol - Maquira",
    "description": "Embalagem com 10ml.",
    "image": "https://cdn.dentalcremer.com.br/produtos/210/frasco-eucaliptol-10ml-maquira-532579.jpg",
    "url": "https://www.dentalcremer.com.br/eucaliptol-maquira-532579.html"
  },
  {
    "sku": "DC30422",
    "name": "Condensador de Guta Mcspadden Maillefer - Dentsply Sirona",
    "description": "Embalagem com 4 unidades. Escolha o modelo.",
    "image": "https://cdn.dentalcremer.com.br/produtos/210/condensador-de-guta-mcspadden-maillefer-dentsply-sirona-dc30422.jpg",
    "url": "https://www.dentalcremer.com.br/condensador-de-guta-mcspadden-maillefer-dentsply-sirona-dc30422.html"
  },
  {
    "sku": "115232",
    "name": "Teste de Vitalidade Endo Ice Spray - Maquira",
    "description": "Embalagem com 1 unidade de 200ml.",
    "image": "https://cdn.dentalcremer.com.br/produtos/210/teste-de-vitalidade-endo-ice-spray-maquira-384987-dental-cremer-1.jpg",
    "url": "https://www.dentalcremer.com.br/teste-de-vitalidade-endo-ice-spray-maquira-115232.html"
  },
  {
    "sku": "731026",
    "name": "Protetor Pulpar Theracal LC - Bisco",
    "description": "Embalagem com 1g.",
    "image": "https://cdn.dentalcremer.com.br/produtos/210/731026_635962405181915806.jpg",
    "url": "https://www.dentalcremer.com.br/protetor-pulpar-theracal-lc-bisco-731026.html"
  }
]